{"data":{"allFile":{"edges":[{"node":{"relativePath":"components/index.js","prettySize":"61 B","extension":"js","birthTime":"38 minutes ago"}},{"node":{"relativePath":"styles/global.scss","prettySize":"69 B","extension":"scss","birthTime":"10 minutes ago"}},{"node":{"relativePath":"pages/index.js","prettySize":"514 B","extension":"js","birthTime":"3 minutes ago"}},{"node":{"relativePath":"components/Grid/index.js","prettySize":"169 B","extension":"js","birthTime":"38 minutes ago"}}]}},"pageContext":{"isCreatedByStatefulCreatePages":true}}